binary_tree/__init__.py
binary_tree/example.py
binary_tree/node.py
binary_tree/tree.py
binary_tree-0.0.1.dist-info/LICENSE
binary_tree-0.0.1.dist-info/METADATA
binary_tree-0.0.1.dist-info/WHEEL
binary_tree-0.0.1.dist-info/top_level.txt
binary_tree-0.0.1.dist-info/RECORD
