Metadata-Version: 2.1
Name: binary_tree
Version: 0.0.1
Summary: Binary_tree is a simple package to create sort and search data with binary trees.
Home-page: https://github.com/Okirshen/binary_tree
Author: Ofri Kirshen
Author-email: okirshen@gmail.com
License: UNKNOWN
Platform: UNKNOWN
Classifier: Programming Language :: Python :: 3
Classifier: License :: OSI Approved :: MIT License
Classifier: Operating System :: OS Independent
